Metadata-Version: 2.1
Name: scrapy-requests-downloader
Version: 1.0.0
Summary: Scrapy middleware with requests support as an alternative to Twisted calls.
Home-page: https://github.com/8W9aG/scrapy-requests-downloader
Author: Will Sackfield
Author-email: will.sackfield@gmail.com
License: MIT
Keywords: scrapy middleware requests
Platform: UNKNOWN
Classifier: License :: OSI Approved :: MIT License
Classifier: Programming Language :: Python :: 3
Classifier: Framework :: Scrapy
License-File: LICENSE
